ai_agent_state/__init__.py
ai_agent_state/state.py
ai_agent_state-0.1.15.dist-info/LICENSE
ai_agent_state-0.1.15.dist-info/METADATA
ai_agent_state-0.1.15.dist-info/WHEEL
ai_agent_state-0.1.15.dist-info/top_level.txt
ai_agent_state-0.1.15.dist-info/RECORD
