Metadata-Version: 2.1
Name: ai-agent-state
Version: 0.1.15
Summary: A library for managing state machines in AI agents
Home-page: https://github.com/AlgorithmicResearchGroup/Agent-States
Author: Algorithmic Research Group
Author-email: matt@algorithmicresearchgroup.com
Classifier: Development Status :: 3 - Alpha
Classifier: Intended Audience :: Developers
Classifier: License :: OSI Approved :: MIT License
Classifier: Operating System :: OS Independent
Classifier: Programming Language :: Python :: 3
Classifier: Programming Language :: Python :: 3.7
Classifier: Programming Language :: Python :: 3.8
Classifier: Programming Language :: Python :: 3.9
Classifier: Programming Language :: Python :: 3.10
Requires-Python: >=3.7
License-File: LICENSE
Requires-Dist: chromadb
Requires-Dist: openai
Requires-Dist: python-dotenv
Requires-Dist: numpy
Requires-Dist: pandas
Requires-Dist: tqdm
Requires-Dist: sentence-transformers
Requires-Dist: typing-extensions
Provides-Extra: dev
Requires-Dist: pytest; extra == "dev"
Requires-Dist: pytest-cov; extra == "dev"
Provides-Extra: viz
Requires-Dist: graphviz; extra == "viz"
